converters/__init__.py
converters/_utils.py
converters/contrib/__init__.py
converters/contrib/country.py
converters/contrib/dataframe.py
converters/contrib/datetime.py
converters/contrib/django_model.py
converters/contrib/django_model_xml.py
converters/contrib/money.py
converters/contrib/str.py
converters/contrib/xml.py
converters/converter.py
python_converters-0.1.1.dist-info/LICENSE.txt
python_converters-0.1.1.dist-info/METADATA
python_converters-0.1.1.dist-info/WHEEL
python_converters-0.1.1.dist-info/RECORD
