Metadata-Version: 2.1
Name: python-converters
Version: 0.1.1
Summary: Write conversions between python objects using an expressive and declarative class-based API
Home-page: https://github.com/The7BridgesTeam/Converters
License: Apache-2.0
Author: 7bridges
Author-email: os@the7bridges.com
Requires-Python: >=3.8.1,<4
Classifier: License :: OSI Approved :: Apache Software License
Classifier: Programming Language :: Python :: 3
Classifier: Programming Language :: Python :: 3.9
Classifier: Programming Language :: Python :: 3.10
Classifier: Programming Language :: Python :: 3.11
Provides-Extra: all
Provides-Extra: datetime
Provides-Extra: django
Provides-Extra: django-xml
Provides-Extra: moneyed
Provides-Extra: pandas
Provides-Extra: unidecode
Provides-Extra: xml
Requires-Dist: Django (>=2.1) ; extra == "django" or extra == "django-xml" or extra == "all"
Requires-Dist: Unidecode (>=1.2.0) ; extra == "django-xml" or extra == "unidecode" or extra == "all"
Requires-Dist: django-countries (>=7.1) ; extra == "django" or extra == "django-xml" or extra == "all"
Requires-Dist: lxml (>=4.6.3) ; extra == "django-xml" or extra == "xml" or extra == "all"
Requires-Dist: pandas (>=0.25.3) ; extra == "pandas" or extra == "all"
Requires-Dist: py-moneyed (>=1.2) ; extra == "moneyed" or extra == "all"
Requires-Dist: pydash (>=4.9.3)
Requires-Dist: python-dateutil (>=2.8.1) ; extra == "datetime" or extra == "all"
Requires-Dist: pytz (>=2021.1) ; extra == "datetime" or extra == "all"
Project-URL: Repository, https://github.com/The7BridgesTeam/Converters
